{
  "indexes": [
    {
      "collectionGroup": "predictions",
      "queryScope": "COLLECTION",
      "fields": [
        { "fieldPath": "matchId", "order": "ASCENDING" },
        { "fieldPath": "uid",     "order": "ASCENDING" }
      ]
    },
    {
      "collectionGroup": "predictions",
      "queryScope": "COLLECTION",
      "fields": [
        { "fieldPath": "uid",     "order": "ASCENDING" },
        { "fieldPath": "savedAt", "order": "DESCENDING" }
      ]
    },
    {
      "collectionGroup": "payments",
      "queryScope": "COLLECTION",
      "fields": [
        { "fieldPath": "uid",       "order": "ASCENDING" },
        { "fieldPath": "createdAt", "order": "DESCENDING" }
      ]
    },
    {
      "collectionGroup": "users",
      "queryScope": "COLLECTION",
      "fields": [
        { "fieldPath": "status",    "order": "ASCENDING" },
        { "fieldPath": "totalPts",  "order": "DESCENDING" }
      ]
    }
  ],
  "fieldOverrides": []
}
